fuckooredoo/__init__.py
fuckooredoo/__main__.py
fuckooredoo/gui.py
fuckooredoo/install_tkinter.py
fuckooredoo/main.py
fuckooredoo/torrent_client.py
fuckooredoo-1.0.2.dist-info/licenses/LICENSE
fuckooredoo-1.0.2.dist-info/METADATA
fuckooredoo-1.0.2.dist-info/WHEEL
fuckooredoo-1.0.2.dist-info/entry_points.txt
fuckooredoo-1.0.2.dist-info/top_level.txt
fuckooredoo-1.0.2.dist-info/RECORD
