Metadata-Version: 2.4
Name: fuckooredoo
Version: 1.0.2
Summary: Secure Torrent Downloader with Tor-based Anti-Throttling - Bypasses ISP throttling through Tor network routing and traffic encryption
Author-email: Mohamed Aziz Bahloul <aziz.bahloul@example.com>
Project-URL: Homepage, https://github.com/AzizBahloul/F_ooredoo
Project-URL: Bug Tracker, https://github.com/AzizBahloul/F_ooredoo/issues
Project-URL: Source Code, https://github.com/AzizBahloul/F_ooredoo
Keywords: torrent,downloader,tor,anti-throttling,isp-bypass,bittorrent,p2p
Classifier: Development Status :: 5 - Production/Stable
Classifier: Intended Audience :: End Users/Desktop
Classifier: Topic :: Communications :: File Sharing
Classifier: Programming Language :: Python :: 3
Classifier: Programming Language :: Python :: 3.8
Classifier: Programming Language :: Python :: 3.9
Classifier: Programming Language :: Python :: 3.10
Classifier: Programming Language :: Python :: 3.11
Classifier: Programming Language :: Python :: 3.12
Classifier: Operating System :: OS Independent
Classifier: Environment :: X11 Applications
Classifier: Environment :: Win32 (MS Windows)
Classifier: Environment :: MacOS X
Requires-Python: >=3.8
Requires-Dist: libtorrent>=2.0.9
Requires-Dist: customtkinter>=5.2.0
Requires-Dist: Pillow>=10.0.0
Requires-Dist: darkdetect>=0.8.0
Requires-Dist: typing-extensions>=4.8.0
